curl2py/__init__.py
curl2py/__main__.py
curl2py/curlParseTool.py
filediff/__init__.py
filediff/__main__.py
filediff/diff.py
filestools/XlsxDataReader.py
filestools/__init__.py
filestools/langconv/__init__.py
filestools/langconv/zh_wiki.py
treedir/__init__.py
treedir/__main__.py
treedir/tree.py
watermarker/__init__.py
watermarker/__main__.py
watermarker/marker.py
watermarker/font/bird.ttf
filestools-0.2.1.dist-info/LICENSE
filestools-0.2.1.dist-info/METADATA
filestools-0.2.1.dist-info/WHEEL
filestools-0.2.1.dist-info/entry_points.txt
filestools-0.2.1.dist-info/top_level.txt
filestools-0.2.1.dist-info/zip-safe
filestools-0.2.1.dist-info/RECORD
