Metadata-Version: 2.1
Name: filestools
Version: 0.2.1
Summary: 文本读写，简繁转换，xlsx纯数据迭代读取，仿Linux的tree命令、文件差异比较工具、图片加水印和curl请求转python代码。
Author: 小小明
Author-email: 604049322@qq.com
License: GPLv3
Platform: any
Classifier: Programming Language :: Python :: 3
Classifier: License :: OSI Approved :: MIT License
Requires-Python: >=3.6
License-File: LICENSE
Requires-Dist: rich >=9.13.0
Requires-Dist: Pillow
Requires-Dist: chardet
Requires-Dist: lxml
Requires-Dist: defusedxml
Requires-Dist: pyperclip >=1.8.0
